Metadata-Version: 2.1
Name: slackspread
Version: 0.1.1
Summary: Wrappers around gspread and slack API
Home-page: https://slack-and-gspread-tools.readthedocs.io/en/stable/
Author: Romain Damian
Author-email: damian.romain@gmail.com
License: UNKNOWN
Platform: UNKNOWN
License-File: LICENSE
